[
  {
    "typeName": "기본_전사",
    "properties": {
      "Label": "기본 전사",
      "EAlliances": "Player",
      "MaxHealth": 100,
      "HealthRegeneration": 0.5,
      "MoveSpeed": 3.5,
      "DefensivePower": 10,
      "AttackPower": 15,
      "MaxFearPoint": 100,
      "SpriteLoaderKey": "warrior_sprite",
      "AnimationLoaderKey": "warrior_anim",
      "AddressablePath": "Units/Warrior",
      "AutoAttackKeys": [
        "warrior_attack_1",
        "warrior_attack_2",
        ""
      ],
      "SkillKeys": [
        "warrior_skill_1",
        "",
        ""
      ]
    },
    "requiredProperties": [
      "Key",
      "Label"
    ]
  },
  {
    "typeName": "기본_궁수",
    "properties": {
      "Label": "기본 궁수",
      "EAlliances": "Player",
      "MaxHealth": 80,
      "HealthRegeneration": 0.3,
      "MoveSpeed": 4,
      "DefensivePower": 5,
      "AttackPower": 20,
      "MaxFearPoint": 90,
      "SpriteLoaderKey": "archer_sprite",
      "AnimationLoaderKey": "archer_anim",
      "AddressablePath": "Units/Archer",
      "AutoAttackKeys": [
        "archer_attack_1",
        "",
        ""
      ],
      "SkillKeys": [
        "archer_skill_1",
        "archer_skill_2",
        ""
      ]
    },
    "requiredProperties": [
      "Key",
      "Label"
    ]
  }
]